pyqtschema/__init__.py
pyqtschema/__main__.py
pyqtschema/__version__.py
pyqtschema/builder.py
pyqtschema/schema.py
pyqtschema/utils.py
pyqtschema/widgets/__init__.py
pyqtschema/widgets/any_of.py
pyqtschema/widgets/array.py
pyqtschema/widgets/base.py
pyqtschema/widgets/boolean.py
pyqtschema/widgets/color.py
pyqtschema/widgets/enu.py
pyqtschema/widgets/groups.py
pyqtschema/widgets/numeric.py
pyqtschema/widgets/paths.py
pyqtschema/widgets/root.py
pyqtschema/widgets/text.py
pyqtschema/widgets/utils.py
pyqtschema-0.2.0.dist-info/LICENSE
pyqtschema-0.2.0.dist-info/METADATA
pyqtschema-0.2.0.dist-info/WHEEL
pyqtschema-0.2.0.dist-info/top_level.txt
pyqtschema-0.2.0.dist-info/RECORD
