Metadata-Version: 2.1
Name: pyqtschema
Version: 0.2.0
Summary: Convert json-schema to QWidgets
Home-page: https://github.com/amsico/pyqtschema
Author: Amsico
Author-email: amsico@eclipso.eu
Project-URL: Bug Tracker, https://github.com/amsico/pyqtschema/issues
Classifier: Programming Language :: Python :: 3
Classifier: License :: OSI Approved :: MIT License
Classifier: Operating System :: OS Independent
Requires-Python: >=3.8
License-File: LICENSE
